boxer/__init__.py
boxer/__main__.py
boxer/_internal/__init__.py
boxer/_internal/builder.py
boxer/_internal/cli.py
boxer/_internal/transport.py
boxer/_internal/version.py
boxer/builder/__init__.py
boxer/builder/hetzner.py
boxer/builder/qemu.py
boxer/cli/__init__.py
boxer/cli/build.py
boxer/clients/__init__.py
boxer/clients/hetzner.py
boxer/common/__init__.py
boxer/common/constants.py
boxer/common/exceptions.py
boxer/common/network.py
boxer/common/process.py
boxer/transport/__init__.py
boxer/transport/ssh.py
boxer/utils/__init__.py
boxer/utils/hetzner.py
boxer-0.0.4.dist-info/METADATA
boxer-0.0.4.dist-info/WHEEL
boxer-0.0.4.dist-info/entry_points.txt
boxer-0.0.4.dist-info/top_level.txt
boxer-0.0.4.dist-info/RECORD
